python_digest/__init__.py
python_digest/http.py
python_digest/tests.py
python_digest/utils.py
pydigest-1.8.dist-info/AUTHORS
pydigest-1.8.dist-info/LICENSE
pydigest-1.8.dist-info/METADATA
pydigest-1.8.dist-info/WHEEL
pydigest-1.8.dist-info/top_level.txt
pydigest-1.8.dist-info/zip-safe
pydigest-1.8.dist-info/RECORD
