Metadata-Version: 2.1
Name: pydigest
Version: 1.8
Summary: A Python library to aid in implementing HTTP Digest Authentication.
Home-page: http://bitbucket.org/akoha/python-digest/
Author: Akoha Inc.
Author-email: adminmail@akoha.com
Classifier: Development Status :: 5 - Production/Stable
Classifier: Environment :: Web Environment
Classifier: License :: OSI Approved :: BSD License
Classifier: Operating System :: OS Independent
Classifier: Programming Language :: Python
Classifier: Topic :: Software Development :: Libraries :: Python Modules
License-File: LICENSE
License-File: AUTHORS
Requires-Dist: six
